streamlit_calendar_input/__init__.py
streamlit_calendar_input/example.py
streamlit_calendar_input/frontend/build/bootstrap.min.css
streamlit_calendar_input/frontend/build/index.html
streamlit_calendar_input/frontend/build/assets/index-C26EEYkm.css
streamlit_calendar_input/frontend/build/assets/index-DctL7cXl.js
streamlit_calendar_input-0.0.3.dist-info/licenses/LICENSE
streamlit_calendar_input-0.0.3.dist-info/METADATA
streamlit_calendar_input-0.0.3.dist-info/WHEEL
streamlit_calendar_input-0.0.3.dist-info/top_level.txt
streamlit_calendar_input-0.0.3.dist-info/RECORD
